{
  "command_timeout": 5,
  "templates_folder": "00 System/z_Templates",
  "templates_pairs": [
    [
      "",
      ""
    ]
  ],
  "trigger_on_file_creation": true,
  "auto_jump_to_cursor": false,
  "enable_system_commands": false,
  "shell_path": "",
  "user_scripts_folder": "",
  "enable_folder_templates": true,
  "folder_templates": [
    {
      "folder": "NPCs",
      "template": "z_Templates/NPC Template.md"
    },
    {
      "folder": "08 Session Logs",
      "template": "00 System/z_Templates/Session Notes Template.md"
    },
    {
      "folder": "05 Quests/Witcher Contracts",
      "template": "00 System/z_Templates/Contract Template.md"
    },
    {
      "folder": "03 Settlements",
      "template": "00 System/z_Templates/City Template.md"
    }
  ],
  "enable_file_templates": false,
  "file_templates": [
    {
      "regex": ".*",
      "template": ""
    }
  ],
  "syntax_highlighting": true,
  "syntax_highlighting_mobile": false,
  "enabled_templates_hotkeys": [
    ""
  ],
  "startup_templates": [
    ""
  ],
  "intellisense_render": 1
}